README.rst
setup.py
src/easy_timer/__init__.py
src/easy_timer/easy_timer.py
src/easy_timer.egg-info/PKG-INFO
src/easy_timer.egg-info/SOURCES.txt
src/easy_timer.egg-info/dependency_links.txt
src/easy_timer.egg-info/entry_points.txt
src/easy_timer.egg-info/requires.txt
src/easy_timer.egg-info/top_level.txt
src/easy_timer/controller/__init__.py
src/easy_timer/controller/countdown_timer.py
src/easy_timer/setting/__init__.py
src/easy_timer/setting/arg_parser.py
src/easy_timer/setting/setting.py
src/easy_timer/view/__init__.py
src/easy_timer/view/printer.py
src/easy_timer/view/speaker.py
src/easy_timer/view/i18n/__init__.py
src/easy_timer/view/i18n/messages_en.py
src/easy_timer/view/i18n/messages_ja.py