Metadata-Version: 1.0
Name: easy-timer
Version: 0.0.4
Summary: Super Simple Command-line Countdown Timer
Home-page: https://github.com/mogproject/easy-timer
Author: mogproject
Author-email: mogproj@gmail.com
License: Apache 2.0 License
Platform: UNKNOWN
